cvm_sqlite/__init__.py
cvm_sqlite/cvm_data_processor.py
cvm_sqlite/database.py
cvm_sqlite/file_manager.py
cvm_sqlite/utils.py
cvm_sqlite-1.1.2.dist-info/METADATA
cvm_sqlite-1.1.2.dist-info/WHEEL
cvm_sqlite-1.1.2.dist-info/licenses/LICENSE.txt
cvm_sqlite-1.1.2.dist-info/RECORD
