Metadata-Version: 2.4
Name: cvm-sqlite
Version: 1.1.2
Summary: A Python tool for downloading, processing, and storing data from the Brazilian Securities and Exchange Commission (CVM - Comissão de Valores Mobiliários) in a SQLite database.
Project-URL: Homepage, https://github.com/eduresser/cvm-sqlite
Project-URL: Repository, https://github.com/eduresser/cvm-sqlite
Author-email: Eduardo Ramon Resser <eduresser@gmail.com>
License-Expression: MIT
License-File: LICENSE.txt
Classifier: Intended Audience :: Developers
Classifier: Intended Audience :: Financial and Insurance Industry
Classifier: License :: OSI Approved :: MIT License
Classifier: Operating System :: OS Independent
Classifier: Programming Language :: Python :: 3.12
Classifier: Topic :: Office/Business :: Financial
Classifier: Topic :: Software Development :: Libraries :: Python Modules
Requires-Python: >=3.12
Requires-Dist: beautifulsoup4>=4.12.3
Requires-Dist: lxml>=5.0.0
Requires-Dist: pandas>=2.2.3
Requires-Dist: requests>=2.32.3
Requires-Dist: tqdm>=4.67.0
